functional_algorithms/__init__.py
functional_algorithms/_version.py
functional_algorithms/algorithms.py
functional_algorithms/context.py
functional_algorithms/expr.py
functional_algorithms/fpu.py
functional_algorithms/restrict.py
functional_algorithms/rewrite.py
functional_algorithms/signatures.py
functional_algorithms/textimage.py
functional_algorithms/typesystem.py
functional_algorithms/utils.py
functional_algorithms/targets/__init__.py
functional_algorithms/targets/base.py
functional_algorithms/targets/cpp.py
functional_algorithms/targets/numpy.py
functional_algorithms/targets/python.py
functional_algorithms/targets/stablehlo.py
functional_algorithms/targets/symbolic.py
functional_algorithms/targets/xla_client.py
functional_algorithms/tests/__init__.py
functional_algorithms/tests/test_accuracy.py
functional_algorithms/tests/test_algorithms.py
functional_algorithms/tests/test_api.py
functional_algorithms/tests/test_context.py
functional_algorithms/tests/test_expr.py
functional_algorithms/tests/test_fpu.py
functional_algorithms/tests/test_functional_algorithms.py
functional_algorithms/tests/test_restrict.py
functional_algorithms/tests/test_utils.py
functional_algorithms-0.15.0.dist-info/LICENSE
functional_algorithms-0.15.0.dist-info/METADATA
functional_algorithms-0.15.0.dist-info/WHEEL
functional_algorithms-0.15.0.dist-info/top_level.txt
functional_algorithms-0.15.0.dist-info/RECORD
