Metadata-Version: 2.1
Name: functional_algorithms
Version: 0.15.0
Summary: Functional algorithms and implementations
Author-email: Pearu Peterson <pearu.peterson@gmail.com>
License: BSD 3-Clause License
Project-URL: Home, https://github.com/pearu/functional_algorithms
Project-URL: Source, https://github.com/pearu/functional_algorithms
Classifier: Intended Audience :: Developers
Classifier: License :: OSI Approved :: BSD License
Classifier: Operating System :: OS Independent
Classifier: Programming Language :: Python :: 3
Classifier: Topic :: Scientific/Engineering
Classifier: Topic :: Software Development
Requires-Python: >=3.11
License-File: LICENSE
Requires-Dist: black
Requires-Dist: numpy
Requires-Dist: mpmath
Requires-Dist: clang-format
Provides-Extra: test
Requires-Dist: pytest; extra == "test"
Requires-Dist: coverage; extra == "test"
Requires-Dist: pytest-mock; extra == "test"
Provides-Extra: dev
Requires-Dist: pre-commit; extra == "dev"
